README.md
setup.py
car_scraper/__init__.py
car_scraper/__main__.py
car_scraper/car_scraping_1.py
ebay_car_scraper.egg-info/PKG-INFO
ebay_car_scraper.egg-info/SOURCES.txt
ebay_car_scraper.egg-info/dependency_links.txt
ebay_car_scraper.egg-info/requires.txt
ebay_car_scraper.egg-info/top_level.txt
rds_uploader/__init__.py
rds_uploader/rds_scraped_ebay_cars.py
rds_uploader/rds_trial.py
test/__init__.py
test/test_car_scraping_1.py