Metadata-Version: 1.0
Name: ebay-car-scraper
Version: 0.0.1
Summary: Mock package that allows you to find celebrity by date of birth
Home-page: https://github.com/Simeon94/ebay_car_scraper_pypi.git
Author: Simeon Bamgbaye
Author-email: UNKNOWN
License: MIT
Platform: UNKNOWN
